flexvector/__init__.py
flexvector/chroma/__init__.py
flexvector/chroma/_client.py
flexvector/config.py
flexvector/core/__init__.py
flexvector/core/models.py
flexvector/factory.py
flexvector/pgvector/__init__.py
flexvector/pgvector/_client.py
flexvector/qdrant/__init__.py
flexvector/qdrant/_client.py
flexvector/weaviate/__init__.py
flexvector/weaviate/_client.py
flexvector-0.1.2.dist-info/LICENSE
flexvector-0.1.2.dist-info/METADATA
flexvector-0.1.2.dist-info/WHEEL
flexvector-0.1.2.dist-info/entry_points.txt
flexvector-0.1.2.dist-info/RECORD
