Metadata-Version: 2.3
Name: flexvector
Version: 0.1.2
Summary: A simple and intuitive vector database abstraction layer
Keywords: vector database,embeddings,similarity search,rag,ai
Author: Ndamulelo Nemakhavhani
Author-email: info@rihonegroup.com
Requires-Python: >=3.11,<3.13
Classifier: Development Status :: 4 - Beta
Classifier: Intended Audience :: Developers
Classifier: License :: OSI Approved :: MIT License
Classifier: Programming Language :: Python :: 3
Classifier: Programming Language :: Python :: 3.11
Classifier: Programming Language :: Python :: 3.12
Classifier: Programming Language :: Python :: 3.13
Requires-Dist: anthropic (>=0.49.0,<0.50.0)
Requires-Dist: chromadb (>=0.5.23,<0.6.0)
Requires-Dist: fastembed (>=0.6.1,<0.7.0)
Requires-Dist: langchain (>=0.3.23,<0.4.0)
Requires-Dist: langchain-chroma (>=0.2.3,<0.3.0)
Requires-Dist: langchain-community (>=0.3.21,<0.4.0)
Requires-Dist: langchain-docling (>=0.2.0,<0.3.0)
Requires-Dist: langchain-openai (>=0.2.14,<0.3.0)
Requires-Dist: langchain-postgres (>=0.0.14,<0.0.15)
Requires-Dist: langchain-qdrant (>=0.2.0,<0.3.0)
Requires-Dist: langchain-weaviate (>=0.0.4,<0.0.5)
Requires-Dist: llama-index (>=0.12.9,<0.13.0)
Requires-Dist: llama-index-readers-web (>=0.3.3,<0.4.0)
Requires-Dist: llama-index-tools-tavily-research (>=0.3.0,<0.4.0)
Requires-Dist: llama-index-vector-stores-postgres (>=0.4.1,<0.5.0)
Requires-Dist: llama-index-vector-stores-qdrant (>=0.4.2,<0.5.0)
Requires-Dist: loguru (>=0.7.3,<0.8.0)
Requires-Dist: openai (>=1.58.1,<2.0.0)
Requires-Dist: pgvector (>=0.3.6,<0.4.0)
Requires-Dist: psycopg-binary (>=3.2.3,<4.0.0)
Requires-Dist: psycopg2-binary (>=2.9.10,<3.0.0)
Requires-Dist: pydantic-settings (>=2.7.0,<3.0.0)
Requires-Dist: pyyaml (>=6.0.2,<7.0.0)
Requires-Dist: qdrant-client (>=1.12.2,<2.0.0)
Requires-Dist: requests (>=2.32.3,<3.0.0)
Requires-Dist: sqlalchemy (>=2.0.36,<3.0.0)
Requires-Dist: tavily-python (>=0.5.0,<0.6.0)
Requires-Dist: toml (>=0.10.2,<0.11.0)
Requires-Dist: trafilatura (>=2.0.0,<3.0.0)
Requires-Dist: weaviate-client (>=4.10.2,<5.0.0)
Project-URL: Homepage, https://github.com/ndamulelonemakh/flexvector
Project-URL: Repository, https://github.com/ndamulelonemakh/flexvector.git
